nanoflann_ext.cpython-310-x86_64-linux-gnu.so
lpqtree/__init__.py
lpqtree/lpqpydist.py
lpqtree/lpqtree.py
lpqtree-0.0.7.dist-info/licenses/LICENSE
lpqtree-0.0.7.dist-info/METADATA
lpqtree-0.0.7.dist-info/WHEEL
lpqtree-0.0.7.dist-info/top_level.txt
lpqtree-0.0.7.dist-info/RECORD
