Metadata-Version: 2.4
Name: lpqtree
Version: 0.0.7
Summary: Lpq KD Tree, adapted from Nanoflann with Python wrapper
Home-page: https://github.com/StongeEtienne/lpqtree
Author: Etienne St-Onge
Author-email: Firstname.Lastname@usherbrooke.ca
License: BSD 2-Clause
License-File: LICENSE
Requires-Dist: pybind11>=2.8
Requires-Dist: scikit-learn>=1.2
Requires-Dist: numpy>=1.22.3
Requires-Dist: scipy>=1.3.2
Dynamic: author
Dynamic: author-email
Dynamic: description
Dynamic: description-content-type
Dynamic: home-page
Dynamic: license
Dynamic: license-file
Dynamic: requires-dist
Dynamic: summary
